spartans/__init__.py
spartans/core.py
spartans/feature_matrix.py
spartans-0.2.0.dist-info/AUTHORS.rst
spartans-0.2.0.dist-info/LICENSE
spartans-0.2.0.dist-info/METADATA
spartans-0.2.0.dist-info/WHEEL
spartans-0.2.0.dist-info/top_level.txt
spartans-0.2.0.dist-info/RECORD
