Metadata-Version: 2.1
Name: spartans
Version: 0.2.0
Summary: Sparse Tools for Analysis
Home-page: https://github.com/Sentinel-One/spartans
Author: Sentinel-One, Dean Langsam
Author-email: deanla@gmail.com
License: GNU General Public License v3
Keywords: spartans,sparse,matrix,features
Platform: UNKNOWN
Classifier: Development Status :: 2 - Pre-Alpha
Classifier: Intended Audience :: Developers
Classifier: License :: OSI Approved :: GNU General Public License v3 (GPLv3)
Classifier: Natural Language :: English
Classifier: Programming Language :: Python :: 3
Classifier: Programming Language :: Python :: 3.6
Classifier: Programming Language :: Python :: 3.7
Classifier: Programming Language :: Python :: 3.8
Requires-Python: >=3.6
Requires-Dist: numpy (>=0.15)
Requires-Dist: scipy (>=1.0.0)
Requires-Dist: joblib (>=0.14)
